uql/config.py
uql/constants.py
uql/intent.py
uql/model.py
uql/utils/exceptions.py
uql/utils/query.py
uql/utils/select.py
uql/utils/templates.py
uql/utils/types.py
uql/views.py
uql-0.1.0.dist-info/LICENSE
uql-0.1.0.dist-info/WHEEL
uql-0.1.0.dist-info/METADATA
uql-0.1.0.dist-info/RECORD
